{
    "-": "-",
    "name": "Carlos Horacio González Gordillo",
    "mainHeader": "Computer Science Engineer",
    "subHeader": "Software Engineering",
    "legalUrl": "http://creativecommons.org/licenses/by-nc-sa/3.0/",
    "legalLabel": "2022 - carloshglez",
    "contactInfo": {
        "title": "Contact",
        "phone": "+52 (811) 011 36 21",
        "phoneLink": "tel:+528110113621",
        "email": "carlos_3349@hotmail.com",
        "emailLink": "mailto:carlos_3349@hotmail.com",
        "linkedin": "https://mx.linkedin.com/in/carloshglez",
        "skype": "carloshglez",
        "skypeLink": "skype:carloshglez?call",
        "githubLink": "https://github.com/carloshglez",
        "resumePath": "carloshglez.com/cv/CV_CarlosGonzalez.pdf",
        "resumeDownloadLabel": "Download Resume",
        "extraInfo": [
            "Availability to home office work."
        ],
        "contactForm": {
            "title": "Send me a message:",
            "namePlaceholder": "Your name",
            "nameError": "Please, what's your name?",
            "emailPlaceholder": "Your e-mail",
            "emailError": "Please, what's your e-mail?",
            "emailRequiredError": "Please, write a proper e-mail",
            "messagePlaceholder": "Your message...",
            "messageError": "Tell me something :)",
            "buttonLabel": "Send"
        }
    },
    "sections": {
        "welcome": {
            "title": "Hi!",
            "content": [
                "Welcome to my personal site!. I developed this place with the purpose of showing my professional experience through the projects in which I have participated, as well as the skills and knowledge that I have acquired.",
                "I like mobile devices, tablets and other innovative gadgets for solving common problems in daily and professional life. I love to development in mobile and web environments."
            ]
        },
        "career": {
            "title": "My Career",
            "content": [
                "With the knowledge acquired in development of Java, I am confident to implement solutions in embebbed systems, hybrid mobile platforms or native, mainly Android.",
                "I want to acquire techniques for development in more platforms that help to increase productivity in the different technological sectors. I am ready to continue learning, creating new ideas, and do my best effort in the tasks assigned to me."
            ]
        },
        "education": {
            "title": "Education",
            "content": [
                {
                    "degree": "Master Degree: Mobile App Development",
                    "startDate": "2015",
                    "endDate": "2016",
                    "school": "Universidad Internacional de la Rioja",
                    "achievement": []
                },
                {
                    "degree": "Software Engineering / Entrepreneurial Experience",
                    "startDate": "2007",
                    "endDate": "2012",
                    "school": "Instituto Tecnológico y de Estudios Superiores de Monterrey - Campus Central de Veracruz",
                    "achievement": [
                        "Honorable mention for excellence and GPA 95",
                        "CENEVAL EGEL-ISOFT: 'Sobresaliente'"
                    ]
                }
            ]
        },
        "professionalExperience": {
            "title": "Profesional Experience",
            "content": [
                {
                    "company": "Metova, Inc.",
                    "startDate": "2019",
                    "endDate": "Today",
                    "summary": [
                        "Android apps development",
                        "Automation of compilation of mobile applications using Jenkins",
                        "Firebase and Google Play Console accounts manager",
                        "Firebase implementation in different applications",
                        "Management of team tasks following Scrum guidelines",
                        "Project Management tools: Jira and Confluence",
                        "Foreign and multidisciplinary team work"
                    ]
                },
                {
                    "company": "DXC Technologies México",
                    "startDate": "2018",
                    "endDate": "2019",
                    "summary": [
                        "Front-end development with ReactJS / Node / Redux / Webpack focused on components.",
                        "Use of dependencies related to development with ReactJS (npm).",
                        "Level 4 support for compiling and publishing mobile applications.",
                        "Automation of compilation of mobile applications using Jenkins.",
                        "Support and update of Windows and MacOS servers with cordoba, gradle, xcode, reaction, xamarin.",
                        "Execution of Scrum Master in team meetings.",
                        "Management of team tasks following Scrum guidelines.",
                        "Execution of project with Dev-Ops guidelines."
                    ]
                },
                {
                    "company": "Softtek GDL",
                    "startDate": "2017",
                    "endDate": "2018",
                    "summary": [
                        "Support and Development for DXC Technologies México",
                        "Front-End development using ReactJS/Node/Redux/Webpackc component and microservices oriented.",
                        "Dependency manager related to ReactJS development (npm).",
                        "Docker management of microservices",
                        "Jenkins automation scripts."
                    ]
                },
                {
                    "company": "Opanga Networks México",
                    "startDate": "2012",
                    "endDate": "2017",
                    "summary": [
                        "Java Developer (Front-end/Back-end), Spring MVC and Web Services",
                        "Web Development using JSP and PostgreSQL",
                        "Glassfish Server management",
                        "Comunication using Protocol Buffers with Restful Web Services",
                        "Licensing Alghorith Task to manage network troughput.",
                        "Basic Android Development (OAuth 2.0, XML parser, AsyncTask)",
                        "Unit and Integration testing (JUnit / Mockito / Selenium)",
                        "OWASP Security Standard.",
                        "Bash/Shell Scripting.",
                        "New Relic Monitoring."
                    ]
                },
                {
                    "company": "ITESM Campus Central de Veracruz",
                    "startDate": "2008",
                    "endDate": "2011",
                    "summary": [
                        "Developer assistant for professional training.",
                        "Java, PHP development with unit and Integration tests,",
                        "HTML, CSS, jQuery and Android.",
                        "MySQL data management"
                    ]
                }
            ]
        },
        "certificates": {
            "title": "Courses and Certificates",
            "content": [
                {
                    "name": "Lynda.com Online Courses",
                    "date": "2017",
                    "summary": [
                        "Learning Path: Become a React Developer"
                    ]
                },
                {
                    "name": "Cambridge English Language Assessment",
                    "date": "2016",
                    "summary": [
                        "Entry Level Certificate in ESOL International (Europe Level A2) (KEY)",
                        "Overall Score: 136, Pass with Merit"
                    ]
                },
                {
                    "name": "Massachusetts Institute of Technology",
                    "date": "2015",
                    "summary": [
                        "Introduction to Computer Science and Programming (Python)."
                    ]
                },
                {
                    "name": "ITESM Campus Central de Veracruz",
                    "date": "2009-2012",
                    "summary": [
                        "2012: Congress of Industrial and Systems Engineering C12",
                        "2010: 3D model with Maya",
                        "2010: ACM - Latin American Regional Contest, Puebla",
                        "2009: 5S Methodology"
                    ]
                }
            ]
        },
        "knowledge": {
            "title": "Knowledge and Skills",
            "topics": [
                {
                    "title": "Web Technologies",
                    "tools": [
                        {
                            "name": "HTML 5 / CSS 3",
                            "level": 100
                        },
                        {
                            "name": "Javascript (jQuery, Ajax)",
                            "level": 90
                        },
                        {
                            "name": "React JS",
                            "level": 85
                        },
                        {
                            "name": "Spring Web MVC",
                            "level": 90
                        },
                        {
                            "name": "Restful Web Services",
                            "level": 90
                        },
                        {
                            "name": "JSP",
                            "level": 100
                        },
                        {
                            "name": "PHP",
                            "level": 80
                        }
                    ]
                },
                {
                    "title": "Mobile Platforms",
                    "tools": [
                        {
                            "name": "Android",
                            "level": 100
                        },
                        {
                            "name": "Hybrid (Cordova, Progressive Apps, React, Xamarin)",
                            "level": 90
                        },
                        {
                            "name": "iOS",
                            "level": 80
                        }
                    ]
                },
                {
                    "title": "Databases",
                    "tools": [
                        {
                            "name": "MySQL",
                            "level": 100
                        },
                        {
                            "name": "PostgreSQL",
                            "level": 90
                        },
                        {
                            "name": "SQLite",
                            "level": 90
                        },
                        {
                            "name": "ElasticSearch",
                            "level": 80
                        }
                    ]
                },
                {
                    "title": "Server Tools",
                    "tools": [
                        {
                            "name": "XAMPP / LAMPP",
                            "level": 90
                        },
                        {
                            "name": "Git / Mercurial",
                            "level": 100
                        },
                        {
                            "name": "Jenkins",
                            "level": 90
                        },
                        {
                            "name": "Glassfish",
                            "level": 80
                        },
                        {
                            "name": "Docker",
                            "level": 70
                        }
                    ]
                },
                {
                    "title": "Software Development Tools",
                    "tools": [
                        {
                            "name": "Netbeans / Eclipse / Visual Studio Code",
                            "level": 100
                        },
                        {
                            "name": "Android Studio",
                            "level": 100
                        },
                        {
                            "name": "Firebase",
                            "level": 90
                        },
                        {
                            "name": "Bash / Shell Scripts",
                            "level": 90
                        },
                        {
                            "name": "Dreamweaver / Photoshop / Gimp",
                            "level": 90
                        },
                        {
                            "name": "UML Case Tools",
                            "level": 90
                        },
                        {
                            "name": "xCode",
                            "level": 80
                        },
                        {
                            "name": "Amazon Web Services (EC2, S3)",
                            "level": 80
                        },
                        {
                            "name": "Google Cloud Services",
                            "level": 80
                        }
                    ]
                }
            ]
        },
        "briefcase": {
            "title": "My Apps",
            "topics": {
                "profession": [
                    {
                        "title": "TAXI 2.0",
                        "image": "carloshglez.com/logos/tx_logo.png",
                        "gallery": [],
                        "summary": [
                            "All-in-one service to establish a communication link between the taxi driver and the passenger.",
                            "It adds the use of technology in a local city facilitating the public transport service and incrementing quality, eficiency and profits."
                        ],
                        "tools": [
                            "Android",
                            "Python",
                            "AWS",
                            "PostgreSQL"
                        ],
                        "demoUrl": [
                            [
                                "https://play.google.com/store/apps/details?id=mx.touchtaxi.customer",
                                "Android Download"
                            ]
                        ]
                    },
                    {
                        "title": "SmartMenu",
                        "image": "carloshglez.com/logos/smartmenu_logo.png",
                        "gallery": [],
                        "summary": [
                            "All-in-one service for restaurants where the traditional menu evolves to show detailed information to the customers and interact to see how the dishes look like, add them to an order, or request the account. At the same time, it allows management in: sections of the menu, preferences and reports about how your business is working.",
                            "It adds the use of technology in the restaurant business in its processes incrementing quality, production and profits."
                        ],
                        "tools": [
                            "Android",
                            "HTML 5 / CSS 3",
                            "PHP",
                            "MySQL",
                            "Javascript"
                        ],
                        "demoUrl": [
                            [
                                "carloshglez.com/proyectos/personal/SmartMenu-v1.0-release.apk",
                                "Android Download"
                            ]
                        ]
                    },
                    {
                        "title": "SARA (Radiological Administrative System)",
                        "image": "carloshglez.com/logos/sara_logo.png",
                        "gallery": [],
                        "summary": [
                            "Project where the design, development and implementation of a system for the management of a radiological cabinet was accomplished.",
                            "It consists of several modules that cover the different areas of the business such as: patient reception, study capture, administrative reports, catalogs of studies and prices, patient history and radiological interpretation."
                        ],
                        "tools": [
                            "Java",
                            "JSP",
                            "Spring MVC",
                            "MySQL",
                            "Javascript"
                        ],
                        "demoUrl": []
                    },
                    {
                        "title": "Watchman System",
                        "image": "carloshglez.com/logos/vigilantes_logo.png",
                        "gallery": [
                            [
                                "carloshglez.com/pantallas/vigilantes/foto1.jpg",
                                "Abrir sesión"
                            ],
                            [
                                "carloshglez.com/pantallas/vigilantes/foto2.jpg",
                                "Historial de reportes"
                            ],
                            [
                                "carloshglez.com/pantallas/vigilantes/foto3.jpg",
                                "Imprimir historial"
                            ],
                            [
                                "carloshglez.com/pantallas/vigilantes/foto4.jpg",
                                "Comentarios"
                            ],
                            [
                                "carloshglez.com/pantallas/vigilantes/foto5.jpg",
                                "Gestión de vigilantes"
                            ],
                            [
                                "carloshglez.com/pantallas/vigilantes/foto6.jpg",
                                "Recorridos"
                            ]
                        ],
                        "summary": [
                            "System developed for the control of routes, movements and times of the tours of the surveillance personnel.",
                            "It allows to visualize the revisions made in a report format to evaluate the effectiveness of the personnel in their routines and checks by the administrator. It also allows for the management of surveillance personnel and the check-up control team.",
                            "Implemented in the Tecnológico de Monterrey Campus Central of Veracruz with the fundamental objective of maintaining a control and monitoring of the correct work of the personnel of supervision favoring the security in the campus and agility in the event of an emergency."
                        ],
                        "tools": [
                            "Java",
                            "HTML / CSS",
                            "MySQL",
                            "Javascript"
                        ],
                        "demoUrl": []
                    },
                    {
                        "title": "Process Management",
                        "image": "carloshglez.com/logos/procesos_logo.png",
                        "gallery": [
                            [
                                "carloshglez.com/pantallas/procesos/foto1.jpg",
                                "Ver diagrama o manual"
                            ],
                            [
                                "carloshglez.com/pantallas/procesos/foto2.jpg",
                                "Gestión de diagrama o manual"
                            ],
                            [
                                "carloshglez.com/pantallas/procesos/foto3.jpg",
                                "Agregar diagrama"
                            ],
                            [
                                "carloshglez.com/pantallas/procesos/foto4.jpg",
                                "Nuevo proceso"
                            ]
                        ],
                        "summary": [
                            "Web application for the storage and revision of diagrams and manuals of the processes that involve the different areas of the departments. Focused on the self-training of the new human resource in its corresponding area.",
                            "Implemented in the Tecnológico de Monterrey Campus Central of Veracruz with the fundamental objective of maintaining order and control of the processes carried out by the personnel, as well as their study for the rotation of the human resource."
                        ],
                        "tools": [
                            "C#",
                            "HTML / CSS",
                            "SQL Server",
                            "Silverlight"
                        ],
                        "demoUrl": []
                    },
                    {
                        "title": "5S Methodology",
                        "image": "carloshglez.com/logos/programa5s_logo.png",
                        "gallery": [
                            [
                                "carloshglez.com/pantallas/programa5s/foto1.jpg",
                                "Programa de 5S"
                            ],
                            [
                                "carloshglez.com/pantallas/programa5s/foto2.jpg",
                                "Departamentos"
                            ],
                            [
                                "carloshglez.com/pantallas/programa5s/foto3.jpg",
                                "Áreas"
                            ],
                            [
                                "carloshglez.com/pantallas/programa5s/foto4.jpg",
                                "Revisiones 5S"
                            ],
                            [
                                "carloshglez.com/pantallas/programa5s/foto5.jpg",
                                "Agregar revisión"
                            ],
                            [
                                "carloshglez.com/pantallas/programa5s/foto6.jpg",
                                "Método 5S"
                            ]
                        ],
                        "summary": [
                            "Web application to manage the information of the program of quality where it is possible to keep track of evidences, the comments and to take the histories of the internal audits.",
                            "Implemented in the Tecnológico de Monterrey Campus Central de Veracruz with the fundamental objective of raising the quality of service and attention, for which it uses as strategy the methodology of '5S' creating a clean, safe and orderly work environment, in which Facilitates the accomplishment of the daily tasks giving results like services with quality and low costs."
                        ],
                        "tools": [
                            "PHP",
                            "HTML / CSS",
                            "MySQL"
                        ],
                        "demoUrl": [
                            [
                                "carloshglez.com/proyectos/profesional/calidad/index.php",
                                "Ver DEMO"
                            ]
                        ]
                    },
                    {
                        "title": "Braille Display",
                        "image": "carloshglez.com/logos/braille_logo.png",
                        "gallery": [],
                        "summary": [
                            "Project in charge of the research and development team as part of the Social Service of the Tecnológico de Monterrey Campus Central de Veracruz.",
                            "Construction of a low-cost Braille display, a device capable of transforming electronic PDF books into the reading and writing system of blind people, the Braille code. This will reduce the digital trouble that exists for this sector of the population.",
                            "The activities carried out: creation of the use algorithm, software libraries for the translation of books and interaction of the device with the user, development of simulator as prototype."
                        ],
                        "tools": [
                            "C",
                            "Java",
                            "DSL"
                        ],
                        "demoUrl": []
                    },
                    {
                        "title": "Web Site 'Fundación Roma'",
                        "image": "carloshglez.com/logos/fundacion_logo.png",
                        "gallery": [
                            [
                                "carloshglez.com/pantallas/roma/foto1.jpg",
                                "Inicio"
                            ],
                            [
                                "carloshglez.com/pantallas/roma/foto2.jpg",
                                "Contacto"
                            ],
                            [
                                "carloshglez.com/pantallas/roma/foto3.jpg",
                                "Actividades"
                            ],
                            [
                                "carloshglez.com/pantallas/roma/foto4.jpg",
                                "Intro"
                            ]
                        ],
                        "summary": [
                            "Promotion of 'Fundacion Roma A.C.' through information technologies to raise awareness of society and provide guides on the services provided.",
                            "The project implements the design, creation and deployment of a website taking into account the characteristics of Human-Computer Interaction and user needs."
                        ],
                        "tools": [
                            "PHP",
                            "HTML / CSS"
                        ],
                        "demoUrl": []
                    }
                ],
                "academic": [
                    {
                        "title": "Advertising Spots",
                        "image": "carloshglez.com/logos/spots_logo.png",
                        "gallery": [],
                        "summary": [
                            "Application development in Android for tablets that allows to display promotional videos in order to be placed in businesses or commercial establishments.",
                            "Perform a remote synchronization to keep the ads that need to be updated without having to manipulate the device."
                        ],
                        "tools": [
                            "Android"
                        ],
                        "demoUrl": []
                    },
                    {
                        "title": "Software Methodology",
                        "image": "carloshglez.com/logos/metodologia_logo.png",
                        "gallery": [],
                        "summary": [
                            "Real world application that applies temporal reasoning within the context of the processes carried out in the software development lifecycle.",
                            "It determines, from the inconsistencies and redundancies in their relations, the most complete and adaptable methodology in software projects.",
                            "The following methodologies are analyzed: cascade, iterative, spiral."
                        ],
                        "tools": [
                            "Java"
                        ],
                        "demoUrl": []
                    },
                    {
                        "title": "Encryption System",
                        "image": "carloshglez.com/logos/cifrado_logo.png",
                        "gallery": [
                            [
                                "carloshglez.com/pantallas/cifrado/foto1.jpg",
                                "Cifrado MD5"
                            ],
                            [
                                "carloshglez.com/pantallas/cifrado/foto2.jpg",
                                "Cifrado RC4"
                            ],
                            [
                                "carloshglez.com/pantallas/cifrado/foto3.jpg",
                                "Cifrado combinado"
                            ],
                            [
                                "carloshglez.com/pantallas/cifrado/foto4.jpg",
                                "Cifrado de archivos"
                            ]
                        ],
                        "summary": [
                            "In order to demonstrate the results of MD5 and RC4 encryption algorithms, a program was developed that allows the encryption of text phrases or files in MD5, RC4 or in a combination that increases the security of encryption."
                        ],
                        "tools": [
                            "Java"
                        ],
                        "demoUrl": []
                    },
                    {
                        "title": "Online store",
                        "image": "carloshglez.com/logos/tienda_logo.png",
                        "gallery": [
                            [
                                "carloshglez.com/pantallas/tienda/foto1.jpg",
                                "Principal"
                            ],
                            [
                                "carloshglez.com/pantallas/tienda/foto2.jpg",
                                "Buscar Producto"
                            ],
                            [
                                "carloshglez.com/pantallas/tienda/foto3.jpg",
                                "Productos"
                            ],
                            [
                                "carloshglez.com/pantallas/tienda/foto4.jpg",
                                "Revisar Producto"
                            ],
                            [
                                "carloshglez.com/pantallas/tienda/foto5.jpg",
                                "Carrito de Compras"
                            ],
                            [
                                "carloshglez.com/pantallas/tienda/foto6.jpg",
                                "Realizar Compra"
                            ]
                        ],
                        "summary": [
                            "Development of a Business-to-Consumer e-commerce site for the search and sale of products.",
                            "Allow customers to access the product catalog remotely, search and select the products they are going to buy through a shopping cart.",
                            "It implements a section for administrators that allows to manage the products: registrations, declines, and modification of the data of registered products."
                        ],
                        "tools": [
                            "PHP",
                            "HTML / CSS",
                            "MySQL",
                            "Javascript / AJAX"
                        ],
                        "demoUrl": [
                            [
                                "carloshglez.com/proyectos/academicos/TiendaLinea/inicio.php",
                                "Ver DEMO"
                            ]
                        ]
                    },
                    {
                        "title": "Raffles and Sweepstakes",
                        "image": "carloshglez.com/logos/rifa_logo.png",
                        "gallery": [
                            [
                                "carloshglez.com/pantallas/sorteos/foto1.jpg",
                                "Seleccionar archivo"
                            ],
                            [
                                "carloshglez.com/pantallas/sorteos/foto2.jpg",
                                "Generar resultado"
                            ],
                            [
                                "carloshglez.com/pantallas/sorteos/foto3.jpg",
                                "Personalizar mensaje"
                            ],
                            [
                                "carloshglez.com/pantallas/sorteos/foto4.jpg",
                                "Envío de correos"
                            ]
                        ],
                        "summary": [
                            "Application for the resolution of raffles and sweepstakes with the innovation of the use of the mail as means of communication to publish the results.",
                            "It allows reading from a text file the data of the participants to select the winner. You also have the option to send mail to all participants notifying the winner."
                        ],
                        "tools": [
                            "Java"
                        ],
                        "demoUrl": []
                    },
                    {
                        "title": "Travel Agency",
                        "image": "carloshglez.com/logos/agencia_logo.png",
                        "gallery": [
                            [
                                "carloshglez.com/pantallas/viajes/foto1.jpg",
                                "Principal"
                            ],
                            [
                                "carloshglez.com/pantallas/viajes/foto2.jpg",
                                "Origen y Destino"
                            ],
                            [
                                "carloshglez.com/pantallas/viajes/foto3.jpg",
                                "Servicios"
                            ],
                            [
                                "carloshglez.com/pantallas/viajes/foto4.jpg",
                                "Información de Destino"
                            ],
                            [
                                "carloshglez.com/pantallas/viajes/foto5.jpg",
                                "Hotel"
                            ],
                            [
                                "carloshglez.com/pantallas/viajes/foto6.jpg",
                                "Vuelo"
                            ],
                            [
                                "carloshglez.com/pantallas/viajes/foto7.jpg",
                                "Paquete de viaje"
                            ],
                            [
                                "carloshglez.com/pantallas/viajes/foto8.jpg",
                                "Resumen del paquete"
                            ],
                            [
                                "carloshglez.com/pantallas/viajes/foto9.jpg",
                                "Actualizar precios"
                            ],
                            [
                                "carloshglez.com/pantallas/viajes/foto10.jpg",
                                "Gestión de Servicios"
                            ],
                            [
                                "carloshglez.com/pantallas/viajes/foto11.jpg",
                                "Gestión de hoteles"
                            ],
                            [
                                "carloshglez.com/pantallas/viajes/foto12.jpg",
                                "Información de stock"
                            ]
                        ],
                        "summary": [
                            "Project developed for the package management of a travel agency. The system focuses on people who confirm and create customer travel packages. It allows to make hotel reservations, car rentals and airline tickets and cruises. It is also possible to analyze the most relevant tourist information of the registered destinations.",
                            "It includes the option to manage the services offered and the stock of tickets or reservations available."
                        ],
                        "tools": [
                            "Java",
                            "JSP",
                            "HTML / CSS",
                            "MySQL",
                            "Javascript / AJAX"
                        ],
                        "demoUrl": []
                    },
                    {
                        "title": "Congress web site C10",
                        "image": "carloshglez.com/logos/c10_logo.png",
                        "gallery": [
                            [
                                "carloshglez.com/pantallas/congreso/foto1.jpg",
                                "Principal"
                            ],
                            [
                                "carloshglez.com/pantallas/congreso/foto2.jpg",
                                "Sede"
                            ],
                            [
                                "carloshglez.com/pantallas/congreso/foto3.jpg",
                                "Hospedaje"
                            ],
                            [
                                "carloshglez.com/pantallas/congreso/foto4.jpg",
                                "Conferencias"
                            ],
                            [
                                "carloshglez.com/pantallas/congreso/foto5.jpg",
                                "Talleres"
                            ]
                        ],
                        "summary": [
                            "In order to promote the Tenth International Congress of Industrial Engineering and Information Technology, which is held every year by the ITESM veracruz, this website was developed to inform about everything related to the congress."
                        ],
                        "tools": [
                            "Adobe Flash",
                            "PHP",
                            "HTML / CSS",
                            "Javascript / AJAX"
                        ],
                        "demoUrl": [
                            [
                                "carloshglez.com/proyectos/academicos/c10/IntroC10.html",
                                "Ver DEMO"
                            ]
                        ]
                    },
                    {
                        "title": "Parking lot",
                        "image": "carloshglez.com/logos/estacionamiento_logo.png",
                        "gallery": [
                            [
                                "carloshglez.com/pantallas/estacionamiento/foto1.jpg",
                                "Principal"
                            ],
                            [
                                "carloshglez.com/pantallas/estacionamiento/foto2.jpg",
                                "Control de lugares"
                            ],
                            [
                                "carloshglez.com/pantallas/estacionamiento/foto3.jpg",
                                "Entrada de auto"
                            ],
                            [
                                "carloshglez.com/pantallas/estacionamiento/foto4.jpg",
                                "Salida de auto"
                            ],
                            [
                                "carloshglez.com/pantallas/estacionamiento/foto5.jpg",
                                "Cuenta por lugar"
                            ],
                            [
                                "carloshglez.com/pantallas/estacionamiento/foto6.jpg",
                                "Animación de autos I"
                            ],
                            [
                                "carloshglez.com/pantallas/estacionamiento/foto7.jpg",
                                "Animación de autos II"
                            ],
                            [
                                "carloshglez.com/pantallas/estacionamiento/foto8.jpg",
                                "Corte de caja"
                            ],
                            [
                                "carloshglez.com/pantallas/estacionamiento/foto9.jpg",
                                "Historial"
                            ]
                        ],
                        "summary": [
                            "The program represents a simulation for a 24-hour parking lot.",
                            "It is created to facilitate the maintenance and control of parking in terms of the organization of the cars and the rate according to the time parked. It is also possible to keep a profit check.",
                            "It also includes an animation that allows you to see how cars enter and leave from the parking lot."
                        ],
                        "tools": [
                            "java",
                            "MySQL"
                        ],
                        "demoUrl": []
                    }
                ],
                "personal": [
                    {
                        "title": "Chronoverse",
                        "image": "carloshglez.com/logos/reacteroids.png",
                        "gallery": [],
                        "summary": [
                            "Project for ReactJS and agile web techologies learning. Thhis can be deployed and publshed as a progressive app, web app or Android App."
                        ],
                        "tools": [
                            "ReactJS",
                            "HTML 5 / CSS 3",
                            "Javascript",
                            "npm / webpack",
                            "Cordova"
                        ],
                        "demoUrl": [
                            [
                                "../chronoverse/index.html",
                                "Play on Web"
                            ],
                            [
                                "https://play.google.com/store/apps/details?id=com.carloshglez.asteroids&hl=es",
                                "Android Download"
                            ]
                        ]
                    },
                    {
                        "title": "Personal Web Site v2.5",
                        "image": "carloshglez.com/logos/webPersonal_Logo.png",
                        "gallery": [],
                        "summary": [
                            "Developed with the purpose of showing my professional experience through the projects in which I participated, as well as the skills and knowledge that I have acquired. It makes use of different javascript utilities in websites."
                        ],
                        "tools": [
                            "ReactJS",
                            "HTML 5 / CSS 3",
                            "PHP",
                            "Javascript",
                            "jQuery",
                            "Ajax"
                        ],
                        "demoUrl": [
                            [
                                "carloshglez.com/proyectos/personal/carloshglez.com_v2/index.html",
                                "Versión 2"
                            ],
                            [
                                "carloshglez.com/proyectos/personal/carloshglez.com_v1.5/index.php",
                                "Versión 1.5"
                            ],
                            [
                                "carloshglez.com/proyectos/personal/carloshglez.com_v1/index.php",
                                "Versión 1"
                            ]
                        ]
                    },
                    {
                        "title": "Mind Challenge",
                        "image": "carloshglez.com/logos/memorama_Logo.jpg",
                        "gallery": [
                            [
                                "carloshglez.com/pantallas/memorama/foto1.jpg",
                                "Principal"
                            ],
                            [
                                "carloshglez.com/pantallas/memorama/foto2.jpg",
                                "Jugo Clásico"
                            ],
                            [
                                "carloshglez.com/pantallas/memorama/foto3.jpg",
                                "Modo de Juego"
                            ],
                            [
                                "carloshglez.com/pantallas/memorama/foto4.jpg",
                                "Juego Experto"
                            ]
                        ],
                        "summary": [
                            "A classic game where the goal is to find 10 pairs discovering the images that are the same.",
                            "Test your memory by playing with the challenge mode to find all the pairs mistakenly the least amount of times, or play in classic mode to have a fun time.",
                            "Be one of the lucky ones discovering all the pairs. But while that happens... How many pairs can you find ...?"
                        ],
                        "tools": [
                            "Java"
                        ],
                        "demoUrl": [
                            [
                                "carloshglez.com/proyectos/personal/Memorama.jar",
                                "Download"
                            ]
                        ]
                    },
                    {
                        "title": "Simon says . . .",
                        "image": "carloshglez.com/logos/simon_Logo.jpg",
                        "gallery": [
                            [
                                "carloshglez.com/pantallas/simon/foto1.jpg",
                                "Principal"
                            ],
                            [
                                "carloshglez.com/pantallas/simon/foto2.jpg",
                                "Modo Campeonato"
                            ],
                            [
                                "carloshglez.com/pantallas/simon/foto3.jpg",
                                "Juego Clásico"
                            ]
                        ],
                        "summary": [
                            "Have fun with this classic game while you exercise your memory. Achieve the challenge of repeating the sequence of the illuminated buttons to win the game.",
                            "You can start with the classic mode or, if you think you're ready, you can try the different game modes it offers.",
                            "You are ready...? Well, let's start: Simon says ..."
                        ],
                        "tools": [
                            "Java"
                        ],
                        "demoUrl": [
                            [
                                "carloshglez.com/proyectos/personal/Simon.jar",
                                "Download"
                            ]
                        ]
                    },
                    {
                        "title": "Looking for the Treasure",
                        "image": "carloshglez.com/logos/tesoro_Logo.jpg",
                        "gallery": [
                            [
                                "carloshglez.com/pantallas/tesoro/foto1.jpg",
                                "Principal"
                            ],
                            [
                                "carloshglez.com/pantallas/tesoro/foto2.jpg",
                                "Nievles de Juego"
                            ],
                            [
                                "carloshglez.com/pantallas/tesoro/foto3.jpg",
                                "Contrareloj"
                            ],
                            [
                                "carloshglez.com/pantallas/tesoro/foto4.jpg",
                                "Modo de Juego"
                            ],
                            [
                                "carloshglez.com/pantallas/tesoro/foto5.jpg",
                                "Progreso con claves"
                            ]
                        ],
                        "summary": [
                            "Try your luck to find the treasure that is hidden in some of the chests before the time runs out.",
                            "Become the best treasure hunter, finding help tracks and winning in the different game modes."
                        ],
                        "tools": [
                            "Java"
                        ],
                        "demoUrl": [
                            [
                                "carloshglez.com/proyectos/personal/Tesoro.jar",
                                "Download"
                            ]
                        ]
                    },
                    {
                        "title": "Cat's game",
                        "image": "carloshglez.com/logos/gato_Logo.jpg",
                        "gallery": [
                            [
                                "carloshglez.com/pantallas/gato/foto1.jpg",
                                "Principal"
                            ],
                            [
                                "carloshglez.com/pantallas/gato/foto2.jpg",
                                "Jugando"
                            ],
                            [
                                "carloshglez.com/pantallas/gato/foto3.jpg",
                                "Jugadores"
                            ]
                        ],
                        "summary": [
                            "The classic cat game, also known as 'Tic Tac Toe' or 'Three in a Row', in a new version. You can play between two players or face a challenge to beat the computer.",
                            "Relive this game and show your skills by finding the cat locked up."
                        ],
                        "tools": [
                            "Java"
                        ],
                        "demoUrl": [
                            [
                                "carloshglez.com/proyectos/personal/Gato.jar",
                                "Download"
                            ]
                        ]
                    },
                    {
                        "title": "Calendar",
                        "image": "carloshglez.com/logos/calendario_Logo.jpg",
                        "gallery": [
                            [
                                "carloshglez.com/pantallas/calendario/foto1.jpg",
                                "Principal"
                            ],
                            [
                                "carloshglez.com/pantallas/calendario/foto2.jpg",
                                "Seleccionar Mes"
                            ],
                            [
                                "carloshglez.com/pantallas/calendario/foto3.jpg",
                                "Configurar Reloj"
                            ]
                        ],
                        "summary": [
                            "A simple application to view the current date and time. You can also browse and view the months. You can also change the clock format and search for a date with the month and year. <br>It is a very useful tool that can not miss to use with your agenda."
                        ],
                        "tools": [
                            "Java"
                        ],
                        "demoUrl": [
                            [
                                "carloshglez.com/proyectos/personal/Calendario.jar",
                                "Download"
                            ]
                        ]
                    }
                ]
            }
        }
    }
}
